fetch/__init__.py
fetch/const.py
fetch/fetch.py
at_fetch_data-1.0.5.dist-info/METADATA
at_fetch_data-1.0.5.dist-info/WHEEL
at_fetch_data-1.0.5.dist-info/top_level.txt
at_fetch_data-1.0.5.dist-info/RECORD
