Metadata-Version: 2.1
Name: at-fetch-data
Version: 1.0.5
Summary: UNKNOWN
Author: ctwel
License: MIT
Platform: UNKNOWN
Requires-Dist: pandas (>=1.0.0)
Requires-Dist: httpx (>=0.24.0)
